setup.py
snappy.py
test_snappy.py
test_snappy_cffi.py
_snappy.pyd
__init__.py
aff4_snappy-0.5.dist-info/DESCRIPTION.rst
aff4_snappy-0.5.dist-info/METADATA
aff4_snappy-0.5.dist-info/metadata.json
aff4_snappy-0.5.dist-info/RECORD
aff4_snappy-0.5.dist-info/top_level.txt
aff4_snappy-0.5.dist-info/WHEEL
